expand_utils.so
fnmatch_vendor.so
carbon_index/__init__.py
carbon_index/index.py
carbon_index/node.py
carbon_index-0.1.11.dist-info/DESCRIPTION.rst
carbon_index-0.1.11.dist-info/METADATA
carbon_index-0.1.11.dist-info/RECORD
carbon_index-0.1.11.dist-info/WHEEL
carbon_index-0.1.11.dist-info/metadata.json
carbon_index-0.1.11.dist-info/top_level.txt
tests/__init__.py
tests/conftest.py
tests/test_benchmark.py
tests/test_index.py
tests/test_node.py
