Metadata-Version: 2.0
Name: carbon-index
Version: 0.1.11
Summary: UNKNOWN
Home-page: UNKNOWN
Author: Yun Xu
Author-email: yunxu1992@gmail.com
License: UNKNOWN
Platform: UNKNOWN
Classifier: Development Status :: 3 - Alpha
Classifier: Operating System :: MacOS
Classifier: Operating System :: POSIX :: Linux
Classifier: Topic :: System :: Software Distribution
Classifier: License :: OSI Approved :: MIT License
Classifier: Programming Language :: Python
Classifier: Programming Language :: Python :: 3
Classifier: Programming Language :: Python :: 3.5
Requires-Dist: lru-dict
